iowarp_core/__init__.py
iowarp_core/_cli.py
iowarp_core/bin/chi_refresh_repo
iowarp_core/bin/chimaera_compose
iowarp_core/bin/chimaera_start_runtime
iowarp_core/bin/chimaera_stop_runtime
iowarp_core/bin/test_binary_assim
iowarp_core/bin/test_error_handling
iowarp_core/bin/test_hdf5_assim
iowarp_core/bin/test_range_assim
iowarp_core/bin/wrp_cae_omni
iowarp_core/include/adapter/H5FDhermes.h
iowarp_core/include/adapter/abstract_mapper.h
iowarp_core/include/adapter/adapter_constants.h
iowarp_core/include/adapter/adapter_types.h
iowarp_core/include/adapter/balanced_mapper.h
iowarp_core/include/adapter/cae_config.h
iowarp_core/include/adapter/cufile_api.h
iowarp_core/include/adapter/filesystem.h
iowarp_core/include/adapter/filesystem_io_client.h
iowarp_core/include/adapter/filesystem_mdm.h
iowarp_core/include/adapter/mapper_factory.h
iowarp_core/include/adapter/mpiio_api.h
iowarp_core/include/adapter/mpiio_fs_api.h
iowarp_core/include/adapter/posix_api.h
iowarp_core/include/adapter/posix_fs_api.h
iowarp_core/include/adapter/stdio_api.h
iowarp_core/include/adapter/stdio_fs_api.h
iowarp_core/include/adapter/filesystem/filesystem.h
iowarp_core/include/adapter/filesystem/filesystem_io_client.h
iowarp_core/include/adapter/filesystem/filesystem_mdm.h
iowarp_core/include/adapter/mapper/abstract_mapper.h
iowarp_core/include/adapter/mapper/balanced_mapper.h
iowarp_core/include/adapter/mapper/mapper_factory.h
iowarp_core/include/adapter/posix/posix_api.h
iowarp_core/include/adapter/posix/posix_fs_api.h
iowarp_core/include/chimaera/admin.h
iowarp_core/include/chimaera/chimaera.h
iowarp_core/include/chimaera/chimaera_manager.h
iowarp_core/include/chimaera/comutex.h
iowarp_core/include/chimaera/config_manager.h
iowarp_core/include/chimaera/container.h
iowarp_core/include/chimaera/corwlock.h
iowarp_core/include/chimaera/integer_timer.h
iowarp_core/include/chimaera/ipc_manager.h
iowarp_core/include/chimaera/module_manager.h
iowarp_core/include/chimaera/pool_manager.h
iowarp_core-0.0.6.dist-info/licenses/LICENSE
iowarp_core-0.0.6.dist-info/METADATA
iowarp_core-0.0.6.dist-info/WHEEL
iowarp_core-0.0.6.dist-info/entry_points.txt
iowarp_core-0.0.6.dist-info/top_level.txt
iowarp_core-0.0.6.dist-info/RECORD
