Metadata-Version: 2.4
Name: iowarp-core
Version: 0.0.6
Summary: IOWarp Core: High-performance distributed I/O and task execution runtime
Author-email: IOWarp Team <grc@illinoistech.edu>
License: BSD
Project-URL: Homepage, https://github.com/iowarp
Project-URL: Bug Tracker, https://github.com/iowarp/iowarp/issues
Keywords: iowarp,hpc,distributed-computing,io-buffering,task-runtime
Classifier: Development Status :: 3 - Alpha
Classifier: Intended Audience :: Developers
Classifier: Intended Audience :: Science/Research
Classifier: License :: OSI Approved :: BSD License
Classifier: Programming Language :: Python :: 3
Classifier: Programming Language :: Python :: 3.8
Classifier: Programming Language :: Python :: 3.9
Classifier: Programming Language :: Python :: 3.10
Classifier: Programming Language :: Python :: 3.11
Classifier: Programming Language :: Python :: 3.12
Classifier: Programming Language :: Python :: 3.13
Classifier: Programming Language :: C++
Classifier: Topic :: System :: Distributed Computing
Classifier: Topic :: Software Development :: Libraries
Requires-Python: >=3.8
License-File: LICENSE
Dynamic: license-file
